<?xml version="1.0" encoding="utf-8" ?>
<dwsync>
<file name="jquery.ui.datepicker-af.js" local="129747786620000000" remote="130065608040000000" testing="0" />
<file name="jquery.ui.datepicker-ar.js" local="129747786620000000" remote="130065608040000000" testing="0" />
<file name="jquery.ui.datepicker-ar-DZ.js" local="129747786620000000" remote="130065608040000000" testing="0" />
<file name="jquery.ui.datepicker-az.js" local="129747786620000000" remote="130065608040000000" testing="0" />
<file name="jquery.ui.datepicker-bg.js" local="129747786620000000" remote="130065608040000000" testing="0" />
<file name="jquery.ui.datepicker-bs.js" local="129747786620000000" remote="130065608040000000" testing="0" />
<file name="jquery.ui.datepicker-ca.js" local="129747786620000000" remote="130065608040000000" testing="0" />
<file name="jquery.ui.datepicker-cs.js" local="129747786620000000" remote="130065608040000000" testing="0" />
<file name="jquery.ui.datepicker-da.js" local="129747786620000000" remote="130065608040000000" testing="0" />
<file name="jquery.ui.datepicker-de.js" local="129747786620000000" remote="130065608040000000" testing="0" />
<file name="jquery.ui.datepicker-el.js" local="129747786620000000" remote="130065608040000000" testing="0" />
<file name="jquery.ui.datepicker-en-AU.js" local="129747786620000000" remote="130065608040000000" testing="0" />
<file name="jquery.ui.datepicker-en-GB.js" local="129747786620000000" remote="130065608040000000" testing="0" />
<file name="jquery.ui.datepicker-en-NZ.js" local="129747786620000000" remote="130065608040000000" testing="0" />
<file name="jquery.ui.datepicker-eo.js" local="129747786620000000" remote="130065608040000000" testing="0" />
<file name="jquery.ui.datepicker-es.js" local="129747786620000000" remote="130065608050000000" testing="0" />
<file name="jquery.ui.datepicker-et.js" local="129747786620000000" remote="130065608050000000" testing="0" />
<file name="jquery.ui.datepicker-eu.js" local="129747786620000000" remote="130065608050000000" testing="0" />
<file name="jquery.ui.datepicker-fa.js" local="129747786620000000" remote="130065608050000000" testing="0" />
<file name="jquery.ui.datepicker-fi.js" local="129747786620000000" remote="130065608050000000" testing="0" />
<file name="jquery.ui.datepicker-fo.js" local="129747786620000000" remote="130065608050000000" testing="0" />
<file name="jquery.ui.datepicker-fr.js" local="129747786620000000" remote="130065608050000000" testing="0" />
<file name="jquery.ui.datepicker-fr-CH.js" local="129747786620000000" remote="130065608050000000" testing="0" />
<file name="jquery.ui.datepicker-gl.js" local="129747786620000000" remote="130065608050000000" testing="0" />
<file name="jquery.ui.datepicker-he.js" local="129747786620000000" remote="130065608050000000" testing="0" />
<file name="jquery.ui.datepicker-hr.js" local="129747786620000000" remote="130065608050000000" testing="0" />
<file name="jquery.ui.datepicker-hu.js" local="129747786620000000" remote="130065608050000000" testing="0" />
<file name="jquery.ui.datepicker-hy.js" local="129747786620000000" remote="130065608050000000" testing="0" />
<file name="jquery.ui.datepicker-id.js" local="129747786620000000" remote="130065608050000000" testing="0" />
<file name="jquery.ui.datepicker-is.js" local="129747786620000000" remote="130065608050000000" testing="0" />
<file name="jquery.ui.datepicker-it.js" local="129747786620000000" remote="130065608050000000" testing="0" />
<file name="jquery.ui.datepicker-ja.js" local="129747786620000000" remote="130065608050000000" testing="0" />
<file name="jquery.ui.datepicker-ko.js" local="129747786620000000" remote="130065608050000000" testing="0" />
<file name="jquery.ui.datepicker-kz.js" local="129747786620000000" remote="130065608050000000" testing="0" />
<file name="jquery.ui.datepicker-lt.js" local="129747786620000000" remote="130065608050000000" testing="0" />
<file name="jquery.ui.datepicker-lv.js" local="129747786620000000" remote="130065608050000000" testing="0" />
<file name="jquery.ui.datepicker-ml.js" local="129747786620000000" remote="130065608050000000" testing="0" />
<file name="jquery.ui.datepicker-ms.js" local="129747786620000000" remote="130065608050000000" testing="0" />
<file name="jquery.ui.datepicker-nl.js" local="129747786620000000" remote="130065608050000000" testing="0" />
<file name="jquery.ui.datepicker-no.js" local="129747786620000000" remote="130065608050000000" testing="0" />
<file name="jquery.ui.datepicker-pl.js" local="129747786620000000" remote="130065608050000000" testing="0" />
<file name="jquery.ui.datepicker-pt.js" local="129747786620000000" remote="130065608050000000" testing="0" />
<file name="jquery.ui.datepicker-pt-BR.js" local="129747786620000000" remote="130065608050000000" testing="0" />
<file name="jquery.ui.datepicker-rm.js" local="129747786620000000" remote="130065608050000000" testing="0" />
<file name="jquery.ui.datepicker-ro.js" local="129747786620000000" remote="130065608050000000" testing="0" />
<file name="jquery.ui.datepicker-ru.js" local="129747786620000000" remote="130065608050000000" testing="0" />
<file name="jquery.ui.datepicker-sk.js" local="129747786620000000" remote="130065608050000000" testing="0" />
<file name="jquery.ui.datepicker-sl.js" local="129747786620000000" remote="130065608050000000" testing="0" />
<file name="jquery.ui.datepicker-sq.js" local="129747786620000000" remote="130065608050000000" testing="0" />
<file name="jquery.ui.datepicker-sr.js" local="129747786620000000" remote="130065608050000000" testing="0" />
<file name="jquery.ui.datepicker-sr-SR.js" local="129747786620000000" remote="130065608050000000" testing="0" />
<file name="jquery.ui.datepicker-sv.js" local="129747786620000000" remote="130065608050000000" testing="0" />
<file name="jquery.ui.datepicker-ta.js" local="129747786620000000" remote="130065608050000000" testing="0" />
<file name="jquery.ui.datepicker-th.js" local="129747786620000000" remote="130065608060000000" testing="0" />
<file name="jquery.ui.datepicker-tj.js" local="129747786620000000" remote="130065608060000000" testing="0" />
<file name="jquery.ui.datepicker-tr.js" local="129747786620000000" remote="130065608060000000" testing="0" />
<file name="jquery.ui.datepicker-uk.js" local="129747786620000000" remote="130065608060000000" testing="0" />
<file name="jquery.ui.datepicker-vi.js" local="129747786620000000" remote="130065608060000000" testing="0" />
<file name="jquery.ui.datepicker-zh-CN.js" local="129747786620000000" remote="130065608060000000" testing="0" />
<file name="jquery.ui.datepicker-zh-HK.js" local="129747786620000000" remote="130065608060000000" testing="0" />
<file name="jquery.ui.datepicker-zh-TW.js" local="129747786620000000" remote="130065608060000000" testing="0" />
<file name="jquery-ui-i18n.js" local="129747786620000000" remote="130065608080000000" testing="0" />
</dwsync>